README.md
setup.py
herdsdk/__init__.py
herdsdk/api_client.py
herdsdk/configuration.py
herdsdk/rest.py
herdsdk.egg-info/PKG-INFO
herdsdk.egg-info/SOURCES.txt
herdsdk.egg-info/dependency_links.txt
herdsdk.egg-info/requires.txt
herdsdk.egg-info/top_level.txt
herdsdk/api/__init__.py
herdsdk/api/allowed_attribute_value_api.py
herdsdk/api/application_api.py
herdsdk/api/attribute_value_list_api.py
herdsdk/api/business_object_data_api.py
herdsdk/api/business_object_data_attribute_api.py
herdsdk/api/business_object_data_notification_registration_api.py
herdsdk/api/business_object_data_status_api.py
herdsdk/api/business_object_data_storage_file_api.py
herdsdk/api/business_object_data_storage_unit_api.py
herdsdk/api/business_object_data_storage_unit_status_api.py
herdsdk/api/business_object_definition_api.py
herdsdk/api/business_object_definition_column_api.py
herdsdk/api/business_object_definition_description_suggestion_api.py
herdsdk/api/business_object_definition_subject_matter_expert_api.py
herdsdk/api/business_object_definition_tag_api.py
herdsdk/api/business_object_format_api.py
herdsdk/api/business_object_format_external_interface_descriptive_information_api.py
herdsdk/api/business_object_format_to_external_interface_mapping_api.py
herdsdk/api/configuration_entry_api.py
herdsdk/api/current_user_api.py
herdsdk/api/custom_ddl_api.py
herdsdk/api/data_provider_api.py
herdsdk/api/emr_api.py
herdsdk/api/emr_cluster_definition_api.py
herdsdk/api/expected_partition_value_api.py
herdsdk/api/external_interface_api.py
herdsdk/api/file_type_api.py
herdsdk/api/global_attribute_definition_api.py
herdsdk/api/index_search_api.py
herdsdk/api/job_api.py
herdsdk/api/job_definition_api.py
herdsdk/api/namespace_api.py
herdsdk/api/namespace_iam_role_authorization_api.py
herdsdk/api/notification_registration_status_api.py
herdsdk/api/partition_key_group_api.py
herdsdk/api/relational_table_registration_api.py
herdsdk/api/search_index_activation_api.py
herdsdk/api/search_index_api.py
herdsdk/api/security_function_api.py
herdsdk/api/security_role_api.py
herdsdk/api/security_role_to_function_mapping_api.py
herdsdk/api/storage_api.py
