Metadata-Version: 1.0
Name: herdsdk
Version: 0.178.0
Summary: herd
Home-page: UNKNOWN
Author: UNKNOWN
Author-email: UNKNOWN
License: UNKNOWN
Keywords: OpenAPI,OpenAPI-Generator,herd
Platform: UNKNOWN
